{
    "fluentMethods": true,
    "relationships": [],
    "fields": [
        {
            "fieldName": "descricao",
            "fieldType": "String",
            "fieldValidateRules": [
                "required"
            ]
        }
    ],
    "changelogDate": "20180406182229",
    "entityTableName": "religiao",
    "dto": "mapstruct",
    "pagination": "pagination",
    "service": "serviceImpl",
    "jpaMetamodelFiltering": false,
    "angularJSSuffix": "caopApp",
    "microserviceName": "caopApp"
}